streamlit_lets_plot/__init__.py
streamlit_lets_plot/lets_plot_chart.py
streamlit_lets_plot/plot_html_helper.py
streamlit_lets_plot_comp-0.2.dev2.dist-info/LICENSE
streamlit_lets_plot_comp-0.2.dev2.dist-info/METADATA
streamlit_lets_plot_comp-0.2.dev2.dist-info/WHEEL
streamlit_lets_plot_comp-0.2.dev2.dist-info/top_level.txt
streamlit_lets_plot_comp-0.2.dev2.dist-info/RECORD
