Metadata-Version: 2.1
Name: streamlit-lets-plot-comp
Version: 0.2.dev2
Summary: A Streamlit component for displaying Lets-Plot charts
Home-page: https://github.com/alshan/streamlit-lets-plot
Author: JetBrains
Author-email: lets-plot@jetbrains.com
Maintainer: JetBrains
Maintainer-email: lets-plot@jetbrains.com
License: MIT
Project-URL: Bug Reports, https://github.com/alshan/streamlit-lets-plot/issues
Project-URL: Source, https://github.com/alshan/streamlit-lets-plot
Classifier: Programming Language :: Python :: 3
Classifier: Programming Language :: Python :: 3.8
Classifier: Programming Language :: Python :: 3.9
Classifier: Programming Language :: Python :: 3.10
Classifier: Programming Language :: Python :: 3.11
Classifier: Programming Language :: Python :: 3.12
Classifier: License :: OSI Approved :: MIT License
Classifier: Operating System :: OS Independent
Classifier: Development Status :: 3 - Alpha
Classifier: Intended Audience :: Developers
Classifier: Topic :: Scientific/Engineering :: Visualization
Requires-Python: >=3.8
License-File: LICENSE
Requires-Dist: streamlit >=0.84.0
Requires-Dist: lets-plot >=4.6.0a1
